{"nodes": [{"id": "agentstepcard_AgentStepCard", "label": "Agent Step Card", "file_type": "code", "source_file": "src/renderer/src/components/agent/AgentStepCard.tsx", "source_location": null, "source_url": null, "captured_at": null, "author": null, "contributor": null}], "edges": [{"source": "agentstepcard_AgentStepCard", "target": "toolcallcard_ToolCallCard", "relation": "references", "confidence": "INFERRED", "confidence_score": 0.95, "source_file": "src/renderer/src/components/agent/AgentStepCard.tsx", "source_location": null, "weight": 1.0}, {"source": "agentstepcard_AgentStepCard", "target": "observationview_ObservationView", "relation": "references", "confidence": "INFERRED", "confidence_score": 0.95, "source_file": "src/renderer/src/components/agent/AgentStepCard.tsx", "source_location": null, "weight": 1.0}, {"source": "agentstepcard_AgentStepCard", "target": "reasoningpanel_ReasoningPanel", "relation": "references", "confidence": "INFERRED", "confidence_score": 0.95, "source_file": "src/renderer/src/components/agent/AgentStepCard.tsx", "source_location": null, "weight": 1.0}, {"source": "agentstepcard_AgentStepCard", "target": "riskbadge_RiskBadge", "relation": "references", "confidence": "INFERRED", "confidence_score": 0.85, "source_file": "src/renderer/src/components/agent/AgentStepCard.tsx", "source_location": null, "weight": 1.0}], "hyperedges": []}