{"nodes": [{"id": "d_local_ai_resources_docker_entrypoint_sh", "label": "entrypoint.sh", "file_type": "code", "source_file": "D:\\Local_AI\\resources\\docker\\entrypoint.sh", "source_location": "L1", "metadata": {"language": "bash", "kind": "file"}}, {"id": "d_local_ai_resources_docker_entrypoint_sh__entry", "label": "entrypoint.sh script", "file_type": "code", "source_file": "D:\\Local_AI\\resources\\docker\\entrypoint.sh", "source_location": "L1", "metadata": {"language": "bash", "kind": "bash_entrypoint"}}], "edges": [{"source": "d_local_ai_resources_docker_entrypoint_sh", "target": "d_local_ai_resources_docker_entrypoint_sh__entry", "relation": "contains", "confidence": "EXTRACTED", "source_file": "D:\\Local_AI\\resources\\docker\\entrypoint.sh", "source_location": "L1", "weight": 1.0}]}